hyppopotamus/__init__.py
hyppopotamus/_version.py
hyppopotamus/hyppopotamus.py
hyppopotamus-0.2.dist-info/DESCRIPTION.rst
hyppopotamus-0.2.dist-info/METADATA
hyppopotamus-0.2.dist-info/RECORD
hyppopotamus-0.2.dist-info/WHEEL
hyppopotamus-0.2.dist-info/entry_points.txt
hyppopotamus-0.2.dist-info/metadata.json
hyppopotamus-0.2.dist-info/top_level.txt
