Metadata-Version: 2.0
Name: hyppopotamus
Version: 0.2
Summary: hyper-parameter optimization
Home-page: http://herve.niderb.fr/
Author: Hervé Bredin
Author-email: bredin@limsi.fr
License: UNKNOWN
Platform: UNKNOWN
Classifier: Development Status :: 4 - Beta
Classifier: Intended Audience :: Science/Research
Classifier: License :: OSI Approved :: MIT License
Classifier: Natural Language :: English
Classifier: Programming Language :: Python :: 2.7
Classifier: Programming Language :: Python :: 3.5
Classifier: Topic :: Scientific/Engineering
Requires-Dist: docopt (>=0.6.2)
Requires-Dist: hyperopt (==0.1)
